{"user_id": "user7", "post_id": "post1", "content": "Just finished my project", "likes": 57, "timestamp": "2023-01-01T00:00:00Z"}
{"user_id": "user3", "post_id": "post2", "content": "Coffee time!", "likes": 10, "timestamp": "2023-01-01T00:05:00Z"}
{"user_id": "user2", "post_id": "post3", "content": "Check out my blog", "likes": 41, "timestamp": "2023-01-01T00:10:00Z"}
{"user_id": "user1", "post_id": "post4", "content": "Just finished my project", "likes": 39, "timestamp": "2023-01-01T00:15:00Z"}
{"user_id": "user2", "post_id": "post5", "content": "Just finished my project", "likes": 98, "timestamp": "2023-01-01T00:20:00Z"}
{"user_id": "user6", "post_id": "post6", "content": "Hello world!", "likes": 79, "timestamp": "2023-01-01T00:25:00Z"}
{"user_id": "user3", "post_id": "post7", "content": "Just posted a photo", "likes": 11, "timestamp": "2023-01-01T00:30:00Z"}
{"user_id": "user8", "post_id": "post8", "content": "Check out my blog", "likes": 16, "timestamp": "2023-01-01T00:35:00Z"}
{"user_id": "user3", "post_id": "post9", "content": "Coffee time!", "likes": 67, "timestamp": "2023-01-01T00:40:00Z"}
{"user_id": "user2", "post_id": "post10", "content": "Just posted a photo", "likes": 94, "timestamp": "2023-01-01T00:45:00Z"}
{"user_id": "user7", "post_id": "post11", "content": "Learning Apache Spark", "likes": 94, "timestamp": "2023-01-01T00:50:00Z"}
{"user_id": "user6", "post_id": "post12", "content": "Lunch time!", "likes": 13, "timestamp": "2023-01-01T00:55:00Z"}
{"user_id": "user1", "post_id": "post13", "content": "Learning Apache Spark", "likes": 47, "timestamp": "2023-01-01T01:00:00Z"}
{"user_id": "user3", "post_id": "post14", "content": "Having a great day!", "likes": 49, "timestamp": "2023-01-01T01:05:00Z"}
{"user_id": "user7", "post_id": "post15", "content": "Check out my blog", "likes": 87, "timestamp": "2023-01-01T01:10:00Z"}
{"user_id": "user5", "post_id": "post16", "content": "Hello world!", "likes": 7, "timestamp": "2023-01-01T01:15:00Z"}
{"user_id": "user3", "post_id": "post17", "content": "Big data is fun", "likes": 75, "timestamp": "2023-01-01T01:20:00Z"}
{"user_id": "user1", "post_id": "post18", "content": "This is a tweet", "likes": 88, "timestamp": "2023-01-01T01:25:00Z"}
{"user_id": "user7", "post_id": "post19", "content": "Having a great day!", "likes": 42, "timestamp": "2023-01-01T01:30:00Z"}
{"user_id": "user8", "post_id": "post20", "content": "Big data is fun", "likes": 30, "timestamp": "2023-01-01T01:35:00Z"}
{"user_id": "user6", "post_id": "post21", "content": "Learning Apache Spark", "likes": 43, "timestamp": "2023-01-01T01:40:00Z"}
{"user_id": "user9", "post_id": "post22", "content": "Just finished my project", "likes": 33, "timestamp": "2023-01-01T01:45:00Z"}
{"user_id": "user5", "post_id": "post23", "content": "Just finished my project", "likes": 13, "timestamp": "2023-01-01T01:50:00Z"}
{"user_id": "user2", "post_id": "post24", "content": "Big data is fun", "likes": 99, "timestamp": "2023-01-01T01:55:00Z"}
{"user_id": "user4", "post_id": "post25", "content": "Coffee time!", "likes": 18, "timestamp": "2023-01-01T02:00:00Z"}
{"user_id": "user5", "post_id": "post26", "content": "Big data is fun", "likes": 49, "timestamp": "2023-01-01T02:05:00Z"}
{"user_id": "user3", "post_id": "post27", "content": "Lunch time!", "likes": 69, "timestamp": "2023-01-01T02:10:00Z"}
{"user_id": "user2", "post_id": "post28", "content": "Big data is fun", "likes": 55, "timestamp": "2023-01-01T02:15:00Z"}
{"user_id": "user4", "post_id": "post29", "content": "Having a great day!", "likes": 9, "timestamp": "2023-01-01T02:20:00Z"}
{"user_id": "user9", "post_id": "post30", "content": "Having a great day!", "likes": 26, "timestamp": "2023-01-01T02:25:00Z"}
{"user_id": "user4", "post_id": "post31", "content": "This is a tweet", "likes": 3, "timestamp": "2023-01-01T02:30:00Z"}
{"user_id": "user4", "post_id": "post32", "content": "Just finished my project", "likes": 91, "timestamp": "2023-01-01T02:35:00Z"}
{"user_id": "user10", "post_id": "post33", "content": "Having a great day!", "likes": 19, "timestamp": "2023-01-01T02:40:00Z"}
{"user_id": "user3", "post_id": "post34", "content": "Coffee time!", "likes": 94, "timestamp": "2023-01-01T02:45:00Z"}
{"user_id": "user5", "post_id": "post35", "content": "Just posted a photo", "likes": 51, "timestamp": "2023-01-01T02:50:00Z"}
{"user_id": "user3", "post_id": "post36", "content": "This is a tweet", "likes": 32, "timestamp": "2023-01-01T02:55:00Z"}
{"user_id": "user7", "post_id": "post37", "content": "Just posted a photo", "likes": 75, "timestamp": "2023-01-01T03:00:00Z"}
{"user_id": "user2", "post_id": "post38", "content": "Lunch time!", "likes": 64, "timestamp": "2023-01-01T03:05:00Z"}
{"user_id": "user6", "post_id": "post39", "content": "Check out my blog", "likes": 43, "timestamp": "2023-01-01T03:10:00Z"}
{"user_id": "user1", "post_id": "post40", "content": "Learning Apache Spark", "likes": 77, "timestamp": "2023-01-01T03:15:00Z"}
{"user_id": "user2", "post_id": "post41", "content": "Learning Apache Spark", "likes": 57, "timestamp": "2023-01-01T03:20:00Z"}
{"user_id": "user3", "post_id": "post42", "content": "This is a tweet", "likes": 49, "timestamp": "2023-01-01T03:25:00Z"}
{"user_id": "user9", "post_id": "post43", "content": "Big data is fun", "likes": 18, "timestamp": "2023-01-01T03:30:00Z"}
{"user_id": "user9", "post_id": "post44", "content": "This is a tweet", "likes": 15, "timestamp": "2023-01-01T03:35:00Z"}
{"user_id": "user2", "post_id": "post45", "content": "Check out my blog", "likes": 75, "timestamp": "2023-01-01T03:40:00Z"}
{"user_id": "user10", "post_id": "post46", "content": "This is a tweet", "likes": 90, "timestamp": "2023-01-01T03:45:00Z"}
{"user_id": "user7", "post_id": "post47", "content": "Lunch time!", "likes": 63, "timestamp": "2023-01-01T03:50:00Z"}
{"user_id": "user1", "post_id": "post48", "content": "Coffee time!", "likes": 6, "timestamp": "2023-01-01T03:55:00Z"}
{"user_id": "user4", "post_id": "post49", "content": "Lunch time!", "likes": 86, "timestamp": "2023-01-01T04:00:00Z"}
{"user_id": "user9", "post_id": "post50", "content": "Big data is fun", "likes": 57, "timestamp": "2023-01-01T04:05:00Z"}
{"user_id": "user4", "post_id": "post51", "content": "Hello world!", "likes": 79, "timestamp": "2023-01-01T04:10:00Z"}
{"user_id": "user2", "post_id": "post52", "content": "Hello world!", "likes": 42, "timestamp": "2023-01-01T04:15:00Z"}
{"user_id": "user4", "post_id": "post53", "content": "Learning Apache Spark", "likes": 49, "timestamp": "2023-01-01T04:20:00Z"}
{"user_id": "user4", "post_id": "post54", "content": "Just posted a photo", "likes": 40, "timestamp": "2023-01-01T04:25:00Z"}
{"user_id": "user2", "post_id": "post55", "content": "Big data is fun", "likes": 51, "timestamp": "2023-01-01T04:30:00Z"}
{"user_id": "user3", "post_id": "post56", "content": "Just finished my project", "likes": 82, "timestamp": "2023-01-01T04:35:00Z"}
{"user_id": "user1", "post_id": "post57", "content": "This is a tweet", "likes": 53, "timestamp": "2023-01-01T04:40:00Z"}
{"user_id": "user9", "post_id": "post58", "content": "This is a tweet", "likes": 26, "timestamp": "2023-01-01T04:45:00Z"}
{"user_id": "user4", "post_id": "post59", "content": "Lunch time!", "likes": 46, "timestamp": "2023-01-01T04:50:00Z"}
{"user_id": "user5", "post_id": "post60", "content": "Just posted a photo", "likes": 57, "timestamp": "2023-01-01T04:55:00Z"}
{"user_id": "user4", "post_id": "post61", "content": "Hello world!", "likes": 65, "timestamp": "2023-01-01T05:00:00Z"}
{"user_id": "user8", "post_id": "post62", "content": "Lunch time!", "likes": 40, "timestamp": "2023-01-01T05:05:00Z"}
{"user_id": "user5", "post_id": "post63", "content": "Just posted a photo", "likes": 18, "timestamp": "2023-01-01T05:10:00Z"}
{"user_id": "user2", "post_id": "post64", "content": "Learning Apache Spark", "likes": 2, "timestamp": "2023-01-01T05:15:00Z"}
{"user_id": "user4", "post_id": "post65", "content": "Learning Apache Spark", "likes": 90, "timestamp": "2023-01-01T05:20:00Z"}
{"user_id": "user4", "post_id": "post66", "content": "Big data is fun", "likes": 34, "timestamp": "2023-01-01T05:25:00Z"}
{"user_id": "user5", "post_id": "post67", "content": "Just posted a photo", "likes": 63, "timestamp": "2023-01-01T05:30:00Z"}
{"user_id": "user1", "post_id": "post68", "content": "Lunch time!", "likes": 37, "timestamp": "2023-01-01T05:35:00Z"}
{"user_id": "user9", "post_id": "post69", "content": "This is a tweet", "likes": 11, "timestamp": "2023-01-01T05:40:00Z"}
{"user_id": "user10", "post_id": "post70", "content": "Big data is fun", "likes": 89, "timestamp": "2023-01-01T05:45:00Z"}
{"user_id": "user9", "post_id": "post71", "content": "Lunch time!", "likes": 65, "timestamp": "2023-01-01T05:50:00Z"}
{"user_id": "user2", "post_id": "post72", "content": "Hello world!", "likes": 54, "timestamp": "2023-01-01T05:55:00Z"}
{"user_id": "user1", "post_id": "post73", "content": "Having a great day!", "likes": 26, "timestamp": "2023-01-01T06:00:00Z"}
{"user_id": "user2", "post_id": "post74", "content": "Hello world!", "likes": 53, "timestamp": "2023-01-01T06:05:00Z"}
{"user_id": "user10", "post_id": "post75", "content": "Hello world!", "likes": 97, "timestamp": "2023-01-01T06:10:00Z"}
{"user_id": "user9", "post_id": "post76", "content": "Lunch time!", "likes": 29, "timestamp": "2023-01-01T06:15:00Z"}
{"user_id": "user1", "post_id": "post77", "content": "Having a great day!", "likes": 18, "timestamp": "2023-01-01T06:20:00Z"}
{"user_id": "user3", "post_id": "post78", "content": "Check out my blog", "likes": 35, "timestamp": "2023-01-01T06:25:00Z"}
{"user_id": "user2", "post_id": "post79", "content": "Having a great day!", "likes": 86, "timestamp": "2023-01-01T06:30:00Z"}
{"user_id": "user10", "post_id": "post80", "content": "Coffee time!", "likes": 15, "timestamp": "2023-01-01T06:35:00Z"}
{"user_id": "user3", "post_id": "post81", "content": "Having a great day!", "likes": 88, "timestamp": "2023-01-01T06:40:00Z"}
{"user_id": "user9", "post_id": "post82", "content": "Just finished my project", "likes": 22, "timestamp": "2023-01-01T06:45:00Z"}
{"user_id": "user10", "post_id": "post83", "content": "This is a tweet", "likes": 70, "timestamp": "2023-01-01T06:50:00Z"}
{"user_id": "user5", "post_id": "post84", "content": "Just posted a photo", "likes": 47, "timestamp": "2023-01-01T06:55:00Z"}
{"user_id": "user2", "post_id": "post85", "content": "Check out my blog", "likes": 50, "timestamp": "2023-01-01T07:00:00Z"}
{"user_id": "user6", "post_id": "post86", "content": "Just posted a photo", "likes": 30, "timestamp": "2023-01-01T07:05:00Z"}
{"user_id": "user7", "post_id": "post87", "content": "Hello world!", "likes": 73, "timestamp": "2023-01-01T07:10:00Z"}
{"user_id": "user6", "post_id": "post88", "content": "Check out my blog", "likes": 62, "timestamp": "2023-01-01T07:15:00Z"}
{"user_id": "user7", "post_id": "post89", "content": "Lunch time!", "likes": 75, "timestamp": "2023-01-01T07:20:00Z"}
{"user_id": "user3", "post_id": "post90", "content": "Lunch time!", "likes": 64, "timestamp": "2023-01-01T07:25:00Z"}
{"user_id": "user6", "post_id": "post91", "content": "Having a great day!", "likes": 77, "timestamp": "2023-01-01T07:30:00Z"}
{"user_id": "user4", "post_id": "post92", "content": "Coffee time!", "likes": 3, "timestamp": "2023-01-01T07:35:00Z"}
{"user_id": "user2", "post_id": "post93", "content": "Coffee time!", "likes": 19, "timestamp": "2023-01-01T07:40:00Z"}
{"user_id": "user1", "post_id": "post94", "content": "This is a tweet", "likes": 99, "timestamp": "2023-01-01T07:45:00Z"}
{"user_id": "user7", "post_id": "post95", "content": "Hello world!", "likes": 34, "timestamp": "2023-01-01T07:50:00Z"}
{"user_id": "user8", "post_id": "post96", "content": "This is a tweet", "likes": 58, "timestamp": "2023-01-01T07:55:00Z"}
{"user_id": "user1", "post_id": "post97", "content": "This is a tweet", "likes": 66, "timestamp": "2023-01-01T08:00:00Z"}
{"user_id": "user9", "post_id": "post98", "content": "Having a great day!", "likes": 95, "timestamp": "2023-01-01T08:05:00Z"}
{"user_id": "user2", "post_id": "post99", "content": "Coffee time!", "likes": 14, "timestamp": "2023-01-01T08:10:00Z"}
{"user_id": "user9", "post_id": "post100", "content": "Having a great day!", "likes": 32, "timestamp": "2023-01-01T08:15:00Z"}
